tasknet/__init__.py
tasknet/models.py
tasknet/tasks.py
tasknet/utils.py
tasknet-1.57.0.dist-info/licenses/LICENSE
tasknet-1.57.0.dist-info/METADATA
tasknet-1.57.0.dist-info/WHEEL
tasknet-1.57.0.dist-info/top_level.txt
tasknet-1.57.0.dist-info/RECORD
