Metadata-Version: 2.4
Name: tasknet
Version: 1.57.0
Summary: Seamless integration of tasks with huggingface models
Home-page: https://github.com/sileod/tasknet/
Classifier: Programming Language :: Python :: 3
Classifier: License :: OSI Approved :: BSD License
Classifier: Intended Audience :: Developers
Requires-Python: >=3.6
License-File: LICENSE
Requires-Dist: torch
Requires-Dist: transformers[torch]
Requires-Dist: datasets
Requires-Dist: evaluate
Requires-Dist: lazy_load
Requires-Dist: easydict
Requires-Dist: frozendict
Requires-Dist: funcy
Requires-Dist: seqeval
Requires-Dist: magicattr
Requires-Dist: sentencepiece
Requires-Dist: tasksource
Dynamic: license-file
